[{
    "model": "auth.user",
    "pk": 2,
    "fields": {
      "password": "pbkdf2_sha256$320000$UcFYhYzHnBfA5Qn3oOyTN1$sC3SkI0rJl54xjvtuHjxDNtn3R1i/QwkfExq1zrvyng=",
      "last_login": null,
      "is_superuser": false,
      "username": "user_one",
      "first_name": "",
      "last_name": "",
      "email": "",
      "is_staff": false,
      "is_active": true,
      "date_joined": "2022-09-26T23:28:00Z",
      "groups": [],
      "user_permissions": []
    }
  }, {
    "model": "auth.user",
    "pk": 3,
    "fields": {
      "password": "pbkdf2_sha256$320000$UcFYhYzHnBfA5Qn3oOyTN1$sC3SkI0rJl54xjvtuHjxDNtn3R1i/QwkfExq1zrvyng=",
      "last_login": null,
      "is_superuser": false,
      "username": "user_two",
      "first_name": "",
      "last_name": "",
      "email": "",
      "is_staff": false,
      "is_active": true,
      "date_joined": "2022-09-26T23:29:00Z",
      "groups": [],
      "user_permissions": []
    }
  }, {
    "model": "auth.user",
    "pk": 4,
    "fields": {
      "password": "pbkdf2_sha256$320000$UcFYhYzHnBfA5Qn3oOyTN1$sC3SkI0rJl54xjvtuHjxDNtn3R1i/QwkfExq1zrvyng=",
      "last_login": null,
      "is_superuser": false,
      "username": "user_three",
      "first_name": "",
      "last_name": "",
      "email": "",
      "is_staff": false,
      "is_active": true,
      "date_joined": "2022-09-26T23:30:00Z",
      "groups": [],
      "user_permissions": []
    }
  }, {
    "model": "auth.user",
    "pk": 5,
    "fields": {
      "password": "pbkdf2_sha256$320000$UcFYhYzHnBfA5Qn3oOyTN1$sC3SkI0rJl54xjvtuHjxDNtn3R1i/QwkfExq1zrvyng=",
      "last_login": null,
      "is_superuser": false,
      "username": "user_four",
      "first_name": "",
      "last_name": "",
      "email": "",
      "is_staff": false,
      "is_active": true,
      "date_joined": "2022-09-26T23:31:00Z",
      "groups": [],
      "user_permissions": []
    }
  }, {
    "model": "auth.user",
    "pk": 6,
    "fields": {
      "password": "pbkdf2_sha256$320000$UcFYhYzHnBfA5Qn3oOyTN1$sC3SkI0rJl54xjvtuHjxDNtn3R1i/QwkfExq1zrvyng=",
      "last_login": null,
      "is_superuser": false,
      "username": "user_five",
      "first_name": "",
      "last_name": "",
      "email": "",
      "is_staff": false,
      "is_active": true,
      "date_joined": "2022-09-26T23:32:00Z",
      "groups": [],
      "user_permissions": []
    }
  }]